tapioca_trustwave/__init__.py
tapioca_trustwave/resource_mapping.py
tapioca_trustwave/tapioca_trustwave.py
tapioca_trustwave_appscanner-0.7.dist-info/METADATA
tapioca_trustwave_appscanner-0.7.dist-info/RECORD
tapioca_trustwave_appscanner-0.7.dist-info/WHEEL
tapioca_trustwave_appscanner-0.7.dist-info/top_level.txt
